examples/example_moku_io_cli.py
mokutools/__init__.py
mokutools/filetools.py
mokutools/phasemeter.py
mokutools/moku_io/__init__.py
mokutools/moku_io/cli.py
mokutools/moku_io/core.py
mokutools/moku_io/notebook.py
mokutools-1.0.1.dist-info/licenses/LICENSE
notebooks/0.0_quickstart.ipynb
notebooks/0.1_cli.ipynb
notebooks/0.2_notebooks.ipynb
notebooks/0.3_phasemeter.ipynb
mokutools-1.0.1.dist-info/METADATA
mokutools-1.0.1.dist-info/WHEEL
mokutools-1.0.1.dist-info/entry_points.txt
mokutools-1.0.1.dist-info/top_level.txt
mokutools-1.0.1.dist-info/RECORD
