Metadata-Version: 2.4
Name: mokutools
Version: 1.0.1
Summary: Liquid Instruments Moku:Lab and Moku:Pro Phasemeter Data Analysis
Author-email: Miguel Dovale <mdovale@arizona.edu>
License: BSD-3-Clause
Project-URL: Homepage, https://github.com/mdovale/mokutools
Project-URL: Documentation, https://github.com/mdovale/mokutools#readme
Project-URL: Repository, https://github.com/mdovale/mokutools
Project-URL: Issues, https://github.com/mdovale/mokutools/issues
Keywords: phasemeter,moku,liquid-instruments,frequency-analysis,phase-analysis,metrology,signal-processing
Classifier: Development Status :: 4 - Beta
Classifier: Intended Audience :: Science/Research
Classifier: License :: OSI Approved :: BSD License
Classifier: Operating System :: OS Independent
Classifier: Programming Language :: Python :: 3
Classifier: Programming Language :: Python :: 3.8
Classifier: Programming Language :: Python :: 3.9
Classifier: Programming Language :: Python :: 3.10
Classifier: Programming Language :: Python :: 3.11
Classifier: Programming Language :: Python :: 3.12
Classifier: Topic :: Scientific/Engineering :: Physics
Classifier: Topic :: Scientific/Engineering :: Information Analysis
Requires-Python: >=3.8
License-File: LICENSE
Requires-Dist: numpy>=1.20.0
Requires-Dist: pandas>=1.3.0
Requires-Dist: scipy>=1.7.0
Requires-Dist: matplotlib>=3.4.0
Requires-Dist: ipywidgets>=7.6.0
Requires-Dist: requests>=2.25.0
Requires-Dist: py7zr>=0.20.0
Requires-Dist: speckit
Requires-Dist: pytdi
Requires-Dist: typer>=0.12.0
Provides-Extra: dev
Requires-Dist: pytest>=7.0.0; extra == "dev"
Requires-Dist: pytest-cov>=3.0.0; extra == "dev"
Requires-Dist: black>=22.0.0; extra == "dev"
Requires-Dist: flake8>=4.0.0; extra == "dev"
Requires-Dist: mypy>=0.950; extra == "dev"
Dynamic: license-file
